odoo/addons/account_invoice_facturx/README.rst
odoo/addons/account_invoice_facturx/__init__.py
odoo/addons/account_invoice_facturx/__manifest__.py
odoo/addons/account_invoice_facturx/hooks.py
odoo/addons/account_invoice_facturx/i18n/account_invoice_factur-x.pot
odoo/addons/account_invoice_facturx/i18n/account_invoice_facturx.pot
odoo/addons/account_invoice_facturx/i18n/de.po
odoo/addons/account_invoice_facturx/i18n/es.po
odoo/addons/account_invoice_facturx/i18n/fr.po
odoo/addons/account_invoice_facturx/i18n/it.po
odoo/addons/account_invoice_facturx/migrations/18.0.2.0.0/pre-migrate.py
odoo/addons/account_invoice_facturx/models/__init__.py
odoo/addons/account_invoice_facturx/models/account_move.py
odoo/addons/account_invoice_facturx/models/ir_actions_report.py
odoo/addons/account_invoice_facturx/models/res_company.py
odoo/addons/account_invoice_facturx/readme/CONFIGURE.md
odoo/addons/account_invoice_facturx/readme/CONTRIBUTORS.md
odoo/addons/account_invoice_facturx/readme/DESCRIPTION.md
odoo/addons/account_invoice_facturx/readme/INSTALL.md
odoo/addons/account_invoice_facturx/static/description/icon.png
odoo/addons/account_invoice_facturx/static/description/index.html
odoo/addons/account_invoice_facturx/static/logos/factur-x-extended.png
odoo/addons/account_invoice_facturx/tests/__init__.py
odoo/addons/account_invoice_facturx/tests/test_facturx_invoice.py
odoo/addons/account_invoice_facturx/views/account_move.xml
odoo/addons/account_invoice_facturx/views/res_partner.xml
odoo_addon_account_invoice_facturx-18.0.2.0.0.4.dist-info/METADATA
odoo_addon_account_invoice_facturx-18.0.2.0.0.4.dist-info/WHEEL
odoo_addon_account_invoice_facturx-18.0.2.0.0.4.dist-info/top_level.txt
odoo_addon_account_invoice_facturx-18.0.2.0.0.4.dist-info/RECORD
