Metadata-Version: 2.1
Name: odoo-addon-account_invoice_facturx
Version: 18.0.2.0.0.4
Requires-Python: >=3.10
Requires-Dist: factur-x
Requires-Dist: odoo-addon-account_einvoice_generate==18.0.*
Requires-Dist: odoo-addon-base_facturx==18.0.*
Requires-Dist: odoo==18.0.*
Summary: Generate Factur-X/ZUGFeRD customer invoices
Home-page: https://github.com/OCA/edi
License: AGPL-3
Author: Akretion,Odoo Community Association (OCA)
Author-email: support@odoo-community.org
Classifier: Programming Language :: Python
Classifier: Framework :: Odoo
Classifier: Framework :: Odoo :: 18.0
Classifier: License :: OSI Approved :: GNU Affero General Public License v3
